{
    "game": {
        "id": "8c089467-8d58-4eff-9a08-f4b9b318c3aa",
        "ruleset": {
            "version": "v1.2.3",
            "settings": {
                "foodSpawnChance": 15,
                "hazardDamagePerTurn": 0,
                "hazardMap": "",
                "hazardMapAuthor": "",
                "minimumFood": 1,
                "royale": {
                    "shrinkEveryNTurns": 0
                },
                "squad": {
                    "allowBodyCollisions": false,
                    "sharedElimination": false,
                    "sharedHealth": false,
                    "sharedLength": false
                }
            },
            "name": "standard"
        },
        "timeout": 500
    },
    "turn": 8,
    "board": {
        "height": 11,
        "width": 11,
        "food": [
            {
                "x": 4,
                "y": 10
            },
            {
                "x": 2,
                "y": 9
            }
        ],
        "snakes": [
            {
                "id": "gs_h4jRyCkqhrtPphgJmySpGGBc",
                "name": "Simple Hungry",
                "health": 100,
                "body": [
                    {
                        "x": 4,
                        "y": 4
                    },
                    {
                        "x": 4,
                        "y": 5
                    },
                    {
                        "x": 4,
                        "y": 6
                    },
                    {
                        "x": 3,
                        "y": 6
                    },
                    {
                        "x": 3,
                        "y": 6
                    }
                ],
                "head": {
                    "x": 4,
                    "y": 4
                },
                "length": 5,
                "latency": "16",
                "shout": ""
            },
            {
                "id": "gs_4K7wxD6FXhW8b3rfG4d6KSfY",
                "name": "Simple Tree Search",
                "health": 94,
                "body": [
                    {
                        "x": 2,
                        "y": 4
                    },
                    {
                        "x": 3,
                        "y": 4
                    },
                    {
                        "x": 3,
                        "y": 3
                    },
                    {
                        "x": 3,
                        "y": 2
                    }
                ],
                "head": {
                    "x": 2,
                    "y": 4
                },
                "length": 4,
                "latency": "19",
                "shout": ""
            },
            {
                "id": "gs_KCTmSFr8XpCQJJqvyRr73t47",
                "name": "Smart Snake",
                "health": 96,
                "body": [
                    {
                        "x": 5,
                        "y": 1
                    },
                    {
                        "x": 5,
                        "y": 2
                    },
                    {
                        "x": 5,
                        "y": 3
                    },
                    {
                        "x": 5,
                        "y": 4
                    }
                ],
                "head": {
                    "x": 5,
                    "y": 1
                },
                "length": 4,
                "latency": "50",
                "shout": ""
            }
        ],
        "hazards": []
    },
    "you": {
        "id": "gs_KCTmSFr8XpCQJJqvyRr73t47",
        "name": "Smart Snake",
        "health": 96,
        "body": [
            {
                "x": 5,
                "y": 1
            },
            {
                "x": 5,
                "y": 2
            },
            {
                "x": 5,
                "y": 3
            },
            {
                "x": 5,
                "y": 4
            }
        ],
        "head": {
            "x": 5,
            "y": 1
        },
        "length": 4,
        "latency": "50",
        "shout": ""
    }
}